LICENSE
MANIFEST.in
README.md
requirements.txt
setup.cfg
setup.py
nuclear_postaladdress.egg-info/PKG-INFO
nuclear_postaladdress.egg-info/SOURCES.txt
nuclear_postaladdress.egg-info/dependency_links.txt
nuclear_postaladdress.egg-info/not-zip-safe
nuclear_postaladdress.egg-info/requires.txt
nuclear_postaladdress.egg-info/top_level.txt
postaladdress/__init__.py
postaladdress/admin.py
postaladdress/apps.py
postaladdress/forms.py
postaladdress/models.py
postaladdress/version.py
postaladdress/widgets.py
postaladdress/locale/en/LC_MESSAGES/django.mo
postaladdress/locale/en/LC_MESSAGES/django.po
postaladdress/locale/hu/LC_MESSAGES/django.mo
postaladdress/locale/hu/LC_MESSAGES/django.po
postaladdress/migrations/0001_initial.py
postaladdress/migrations/__init__.py
postaladdress/static/js/jquery.geocomplete.js
postaladdress/static/js/jquery.geocomplete.min.js
postaladdress/static/postaladdress/js/address.js