Metadata-Version: 2.1
Name: nuclear-postaladdress
Version: 1.0.0
Summary: A django application for describing addresses.
Home-page: https://gitlab.com/cherubits/cherubits-community/nuclear-platform/nuclear-postaladdress
Author: László Hegedűs
Author-email: laszlo.hegedus@cherubits.hu
Maintainer: László Hegedűs
Maintainer-email: laszlo.hegedus@cherubits.hu
License: MIT
Platform: UNKNOWN
Classifier: Development Status :: 3 - Alpha
Classifier: Framework :: Django
Classifier: Framework :: Django :: 3.0
Classifier: Intended Audience :: Developers
Classifier: License :: OSI Approved :: MIT License
Classifier: Natural Language :: English
Classifier: Operating System :: OS Independent
Classifier: Programming Language :: Python
Classifier: Programming Language :: Python :: 3.5
Classifier: Programming Language :: Python :: 3.6
Classifier: Programming Language :: Python :: 3.7
Classifier: Programming Language :: Python :: 3.8
Classifier: Topic :: Database
Classifier: Topic :: Utilities
